streamlit_argparse/__init__.py
streamlit_argparse/argparse_patch.py
streamlit_argparse-0.0.1.dist-info/METADATA
streamlit_argparse-0.0.1.dist-info/WHEEL
streamlit_argparse-0.0.1.dist-info/top_level.txt
streamlit_argparse-0.0.1.dist-info/RECORD
