Metadata-Version: 2.4
Name: streamlit-argparse
Version: 0.0.1
Summary: Generates a form for an argparse Parser
Home-page: https://github.com/streamlit-community/streamlit-navigation-bar
Author: Hans Then
Author-email: hans.then@gmail.com
License: MIT License
Project-URL: Source Code, https://github.com/streamlit-community/streamlit-navigation-bar
Project-URL: Bug Tracker, https://github.com/streamlit-community/streamlit-navigation-bar/issues
Project-URL: Release notes, https://github.com/streamlit-community/streamlit-navigation-bar/releases
Project-URL: Documentation, https://github.com/streamlit-community/streamlit-navigation-bar/wiki/API-reference
Project-URL: Community, https://discuss.streamlit.io/t/new-component-streamlit-navigation-bar/66032
Classifier: Development Status :: 5 - Production/Stable
Classifier: Environment :: Console
Classifier: Environment :: Web Environment
Classifier: Intended Audience :: Developers
Classifier: Intended Audience :: Science/Research
Classifier: License :: OSI Approved :: MIT License
Classifier: Programming Language :: Python :: 3.10
Classifier: Programming Language :: Python :: 3.11
Classifier: Programming Language :: Python :: 3.12
Classifier: Topic :: Database :: Front-Ends
Classifier: Topic :: Software Development :: Widget Sets
Requires-Python: >=3.10
Requires-Dist: streamlit>1.38.0
Requires-Dist: streamlit_tags
Dynamic: author
Dynamic: author-email
Dynamic: classifier
Dynamic: description
Dynamic: description-content-type
Dynamic: home-page
Dynamic: license
Dynamic: project-url
Dynamic: requires-dist
Dynamic: requires-python
Dynamic: summary
